.gitignore
LICENSE.txt
MANIFEST.in
setup.py
stdeb.cfg
motmot/__init__.py
motmot.realtime_image_analysis.egg-info/PKG-INFO
motmot.realtime_image_analysis.egg-info/SOURCES.txt
motmot.realtime_image_analysis.egg-info/dependency_links.txt
motmot.realtime_image_analysis.egg-info/namespace_packages.txt
motmot.realtime_image_analysis.egg-info/not-zip-safe
motmot.realtime_image_analysis.egg-info/top_level.txt
motmot/realtime_image_analysis/__init__.py
motmot/realtime_image_analysis/fit_params.pxd
motmot/realtime_image_analysis/realtime_image_analysis.cpp
motmot/realtime_image_analysis/realtime_image_analysis.pyx
motmot/realtime_image_analysis/slow.py
motmot/realtime_image_analysis/tests.py
src/c_fit_params.cpp
src/c_fit_params.h
src/c_time_time.c
src/c_time_time.h
src/eigen.c
src/eigen.h
src/motmot_ria_macros.h