Metadata-Version: 1.0
Name: motmot.realtime-image-analysis
Version: 0.8.0
Summary: several image analysis functions that require Intel IPP and FastImage
Home-page: http://code.astraw.com/projects/motmot
Author: Andrew Straw
Author-email: strawman@astraw.com
License: BSD
Platform: UNKNOWN
